Metadata-Version: 2.1
Name: myecommerce
Version: 1.0.0
Summary: A simple e-commerce package for managing products, users, and orders.
Home-page: UNKNOWN
Author: Bipul Kumar
Author-email: bipul@example.com
License: UNKNOWN
Platform: UNKNOWN
Classifier: Programming Language :: Python :: 3
Classifier: License :: OSI Approved :: MIT License
Classifier: Operating System :: OS Independent
Requires-Python: >=3.6
